llama_vector/__init__.py
llama_vector/config.py
llama_vector/index.py
llama_vector/quality.py
llama_vector/utils.py
llamavector_llamasearch-0.1.0.dist-info/METADATA
llamavector_llamasearch-0.1.0.dist-info/WHEEL
llamavector_llamasearch-0.1.0.dist-info/licenses/LICENSE
llamavector_llamasearch-0.1.0.dist-info/RECORD
