Metadata-Version: 2.4
Name: llamavector-llamasearch
Version: 0.1.0
Summary: Vector embedding generation, storage, and similarity search for LlamaAI Ecosystem
Project-URL: Homepage, https://github.com/yourusername/llama-vector
Project-URL: Bug Tracker, https://github.com/yourusername/llama-vector/issues
Project-URL: Documentation, https://yourusername.github.io/llama-vector/
Author-email: llamavector-llamasearch <nikjois@llamasearch.ai>
License: MIT License
License-File: LICENSE
Classifier: Development Status :: 3 - Alpha
Classifier: Intended Audience :: Developers
Classifier: License :: OSI Approved :: MIT License
Classifier: Programming Language :: Python :: 3
Classifier: Programming Language :: Python :: 3.8
Classifier: Programming Language :: Python :: 3.9
Classifier: Programming Language :: Python :: 3.10
Classifier: Programming Language :: Python :: 3.11
Classifier: Topic :: Database
Classifier: Topic :: Scientific/Engineering :: Artificial Intelligence
Classifier: Topic :: Software Development :: Libraries :: Python Modules
Requires-Python: >=3.8
Requires-Dist: annoy>=1.17.0
Requires-Dist: chromadb>=0.4.0
Requires-Dist: faiss-cpu>=1.7.3
Requires-Dist: loguru>=0.7.0
Requires-Dist: numpy>=1.21.0
Requires-Dist: pinecone-client>=2.2.0
Requires-Dist: pydantic>=1.10.0
Requires-Dist: qdrant-client>=1.1.0
Requires-Dist: scipy>=1.7.0
Requires-Dist: sentence-transformers>=2.2.0
Requires-Dist: tqdm>=4.60.0
Requires-Dist: weaviate-client>=3.15.0
Provides-Extra: all
Requires-Dist: llama-vector[api,dev,docs]; extra == 'all'
Provides-Extra: api
Requires-Dist: fastapi>=0.95.0; extra == 'api'
Requires-Dist: uvicorn[standard]>=0.21.0; extra == 'api'
Provides-Extra: dev
Requires-Dist: black>=23.3.0; extra == 'dev'
Requires-Dist: isort>=5.12.0; extra == 'dev'
Requires-Dist: mypy>=1.2.0; extra == 'dev'
Requires-Dist: pre-commit>=3.3.1; extra == 'dev'
Requires-Dist: pytest-cov>=4.1.0; extra == 'dev'
Requires-Dist: pytest-mock>=3.10.0; extra == 'dev'
Requires-Dist: pytest>=7.3.1; extra == 'dev'
Requires-Dist: ruff>=0.0.260; extra == 'dev'
Provides-Extra: docs
Requires-Dist: mkdocs-material>=9.1.6; extra == 'docs'
Requires-Dist: mkdocs>=1.4.2; extra == 'docs'
Requires-Dist: mkdocstrings[python]>=0.20.0; extra == 'docs'
